linear_operator_learning/__init__.py
linear_operator_learning/py.typed
linear_operator_learning/kernel/__init__.py
linear_operator_learning/kernel/linalg.py
linear_operator_learning/kernel/regressors.py
linear_operator_learning/kernel/structs.py
linear_operator_learning/kernel/utils.py
linear_operator_learning/nn/__init__.py
linear_operator_learning/nn/functional.py
linear_operator_learning/nn/linalg.py
linear_operator_learning/nn/regressors.py
linear_operator_learning/nn/stats.py
linear_operator_learning/nn/structs.py
linear_operator_learning/nn/modules/__init__.py
linear_operator_learning/nn/modules/ema_covariance.py
linear_operator_learning/nn/modules/loss.py
linear_operator_learning/nn/modules/mlp.py
linear_operator_learning/nn/modules/resnet.py
linear_operator_learning/nn/modules/simnorm.py
linear_operator_learning-0.2.5.dist-info/METADATA
linear_operator_learning-0.2.5.dist-info/WHEEL
linear_operator_learning-0.2.5.dist-info/licenses/LICENSE
linear_operator_learning-0.2.5.dist-info/RECORD
