Metadata-Version: 2.4
Name: linear-operator-learning
Version: 0.2.5
Summary: A package to learn linear operators
Author-email: Alek Frohlich <alek.frohlich@gmail.com>, Pietro Novelli <pietronvll@gmail.com>
License-File: LICENSE
Requires-Python: >=3.10
Requires-Dist: numpy>=1.26
Requires-Dist: scipy>=1.12
Requires-Dist: torch>=2.0
